Metadata-Version: 2.1
Name: torchcpd
Version: 1.0.0
Summary: PyTorch Implementation of the Coherent Point Drift Algorithm
Home-page: https://github.com/ramtingh/torchcpd
Author: Ramtin Gharleghi
Author-email: ramtin@ramt.in
License: MIT
Keywords: image processing,point cloud,registration,mesh,surface
Classifier: Development Status :: 3 - Alpha
Classifier: License :: OSI Approved :: MIT License
Classifier: Programming Language :: Python :: 3.10
Classifier: Programming Language :: Python :: 3.9
Classifier: Programming Language :: Python :: 3.8
Classifier: Programming Language :: Python :: 3.7
Classifier: Topic :: Scientific/Engineering
License-File: LICENSE
